{
    "name": "ThuongLo Hosting",
    "host": "test1.web3b.com",
    "protocol": "ftp",
    "port": 21,
    "username": "thuonglo@test1.web3b.com",
    "password": "21042005nhat",
    "passive": true,
    "secure": false,
    "remotePath": "public_html/",
    "uploadOnSave": true,
    "useTempFile": false,
    "openSsh": false,
    "ignore": [
        ".vscode",
        ".git",
        ".agent",
        ".kiro",
        "logs/*",
        "tmp/*",
        "backups/*",
        "storage/*",
        ".gitignore",
        "README.md"
    ],
    "syncOption": {
        "delete": false,
        "update": true
    },
    "watcher": {
        "files": "**/*",
        "autoUpload": true,
        "autoDelete": false
    }
}